typo_shield/__init__.py
typo_shield/cli.py
typo_shield/config.py
typo_shield/correlator.py
typo_shield/diff.py
typo_shield/git.py
typo_shield/data/module_dist_aliases.json
typo_shield/data/top_packages.txt
typo_shield/mapping/__init__.py
typo_shield/mapping/module_to_dist.py
typo_shield/mapping/project_modules.py
typo_shield/mapping/stdlib.py
typo_shield/report/__init__.py
typo_shield/report/render_json.py
typo_shield/report/render_text.py
typo_shield/risk/__init__.py
typo_shield/risk/models.py
typo_shield/risk/rules.py
typo_shield/risk/score.py
typo_shield/risk/typosquat.py
typo_shield/scanners/__init__.py
typo_shield/scanners/deps_pyproject.py
typo_shield/scanners/deps_requirements.py
typo_shield/scanners/python_imports.py
typo_shield-0.1.1.dist-info/METADATA
typo_shield-0.1.1.dist-info/WHEEL
typo_shield-0.1.1.dist-info/entry_points.txt
typo_shield-0.1.1.dist-info/licenses/LICENSE
typo_shield-0.1.1.dist-info/RECORD
