Metadata-Version: 2.4
Name: typo-shield
Version: 0.1.1
Summary: Security guard against typosquatting in Python dependencies
Project-URL: Homepage, https://github.com/kszmigiel/typo-shield
Project-URL: Repository, https://github.com/kszmigiel/typo-shield
Project-URL: Issues, https://github.com/kszmigiel/typo-shield/issues
Author-email: Kacper <kacper@example.com>
License: MIT
License-File: LICENSE
Keywords: dependencies,pip,pre-commit,pypi,python,security,supply-chain,typosquatting
Classifier: Development Status :: 3 - Alpha
Classifier: Environment :: Console
Classifier: Intended Audience :: Developers
Classifier: License :: OSI Approved :: MIT License
Classifier: Operating System :: OS Independent
Classifier: Programming Language :: Python :: 3
Classifier: Programming Language :: Python :: 3.10
Classifier: Programming Language :: Python :: 3.11
Classifier: Programming Language :: Python :: 3.12
Classifier: Programming Language :: Python :: 3.13
Classifier: Programming Language :: Python :: 3.14
Classifier: Topic :: Security
Classifier: Topic :: Software Development :: Libraries :: Python Modules
Classifier: Topic :: Software Development :: Quality Assurance
Classifier: Typing :: Typed
Requires-Python: >=3.10
Requires-Dist: packaging>=23.0
Requires-Dist: rapidfuzz>=3.0.0
Requires-Dist: tomli>=2.0.0; python_version < '3.11'
Requires-Dist: typer>=0.9.0
Provides-Extra: dev
Requires-Dist: build>=0.10.0; extra == 'dev'
Requires-Dist: mypy>=1.0; extra == 'dev'
Requires-Dist: pre-commit>=3.0; extra == 'dev'
Requires-Dist: pytest-cov>=4.0; extra == 'dev'
Requires-Dist: pytest>=7.0; extra == 'dev'
Requires-Dist: ruff>=0.1.0; extra == 'dev'
Requires-Dist: twine>=4.0.0; extra == 'dev'
